virustotalpy/__init__.py
virustotalpy/wrapper.py
virustotalpy-1.0.1.dist-info/LICENSE
virustotalpy-1.0.1.dist-info/METADATA
virustotalpy-1.0.1.dist-info/WHEEL
virustotalpy-1.0.1.dist-info/top_level.txt
virustotalpy-1.0.1.dist-info/RECORD
