Metadata-Version: 2.1
Name: virustotalpy
Version: 1.0.1
Summary: library for an easier interaction with the VirusTotal v3 API
Home-page: https://github.com/maxmmueller/virustotalpy
Author: Maximilian Müller
License: Apache License 2.0
Platform: UNKNOWN
Classifier: Intended Audience :: Developers
Classifier: Programming Language :: Python
Classifier: Programming Language :: Python :: 3
Classifier: Programming Language :: Python :: 3.6
Classifier: Programming Language :: Python :: 3.7
Classifier: Programming Language :: Python :: 3.8
Classifier: Programming Language :: Python :: 3.9
Classifier: Programming Language :: Python :: 3.10
Classifier: Programming Language :: Python :: 3.11
Classifier: Operating System :: OS Independent
Requires-Dist: requests
